winkicord/__init__.py
winkicord/music.py
winkicord/nodepool.py
winkicord/py.typed
winkicord-1.0.0.dist-info/LICENSE
winkicord-1.0.0.dist-info/METADATA
winkicord-1.0.0.dist-info/WHEEL
winkicord-1.0.0.dist-info/top_level.txt
winkicord-1.0.0.dist-info/RECORD
