Metadata-Version: 2.1
Name: winkicord
Version: 1.0.0
Summary: Effortlessly create a fully functional Discord music bot with just one line of Python code.
Home-page: https://github.com/UjjwalxD/winkicord/
Author: Ujjwal Srivastava
Author-email: Ujjwal Srivastava <ujjwal.winklebot@proton.me>
License: Copyright (c) 2024 @Winkicords,
Project-URL: Homepage, https://github.com/UjjwalxD/winkicord
Project-URL: Issues, https://github.com/UjjwalxD/winkicord/issues
Classifier: Programming Language :: Python :: 3
Classifier: License :: OSI Approved :: MIT License
Classifier: Operating System :: OS Independent
Requires-Python: >=3.10
License-File: LICENSE
Requires-Dist: discord.py==2.4.0
Requires-Dist: wavelink
